vearch_cluster/__init__.py
vearch_cluster-0.0.2.dist-info/METADATA
vearch_cluster-0.0.2.dist-info/WHEEL
vearch_cluster-0.0.2.dist-info/top_level.txt
vearch_cluster-0.0.2.dist-info/RECORD
