Metadata-Version: 2.1
Name: vearch-cluster
Version: 0.0.2
Summary: A library for efficient similarity search and storage of deep learning vectors.
Home-page: https://github.com/vearch/vearch
Author: vearch author
Author-email: vearch-maintainers@groups.io
License: Apache License, Version 2.0
Keywords: real time index,vector nearest neighbors
